croissant/__init__.py
croissant/features.py
croissant/ingest.py
croissant/roi.py
croissant/train.py
croissant/utils.py
croissant_ml-0.0.1a0.dist-info/LICENSE.md
croissant_ml-0.0.1a0.dist-info/METADATA
croissant_ml-0.0.1a0.dist-info/WHEEL
croissant_ml-0.0.1a0.dist-info/top_level.txt
croissant_ml-0.0.1a0.dist-info/RECORD
