Metadata-Version: 2.1
Name: croissant-ml
Version: 0.0.1a0
Summary: Classification of neurons segmented from two photonmicroscopy videos
Home-page: https://github.com/AllenInstitute/croissant
Author: Kat Schelonka, Isaak Willett, Dan Kapner, Nicholas Mei
Author-email: kat.schelonka@alleninstitute.org
License: UNKNOWN
Platform: UNKNOWN
Classifier: Development Status :: 3 - Alpha
Classifier: Intended Audience :: Science/Research
Classifier: Programming Language :: Python :: 3.8
Requires-Python: >=3.8
Requires-Dist: pytest
Requires-Dist: pytest-cov
Requires-Dist: pandas (>=1.0.0)
Requires-Dist: scikit-learn (>=0.23.1)
Requires-Dist: numpy
Requires-Dist: scipy
Requires-Dist: argschema (==2.0.1)
Requires-Dist: setuptools
Requires-Dist: mlflow
Requires-Dist: tables
Requires-Dist: boto3
Requires-Dist: moto
Requires-Dist: jsonlines
Requires-Dist: s3fs
